brightest_path_lib/__init__.py
brightest_path_lib/_myVersion.py
brightest_path_lib/checkNumba.py
brightest_path_lib/algorithm/__init__.py
brightest_path_lib/algorithm/astar.py
brightest_path_lib/algorithm/nbastar.py
brightest_path_lib/algorithm/numba_nbastar.py
brightest_path_lib/cost/__init__.py
brightest_path_lib/cost/cost.py
brightest_path_lib/cost/reciprocal.py
brightest_path_lib/cost/reciprocal_transonic.py
brightest_path_lib/heuristic/__init__.py
brightest_path_lib/heuristic/euclidean.py
brightest_path_lib/heuristic/euclidean_transonic.py
brightest_path_lib/heuristic/heuristic.py
brightest_path_lib/image/__init__.py
brightest_path_lib/image/stats.py
brightest_path_lib/input/__init__.py
brightest_path_lib/input/inputs.py
brightest_path_lib/node/__init__.py
brightest_path_lib/node/bidirectional_node.py
brightest_path_lib/node/node.py
brightest_path_lib-1.0.57.dist-info/licenses/LICENSE
data/sample-2d.tif
data/sample-3d.csv
data/sample-3d.tif
docs/about.md
docs/api_docs.md
docs/index.md
docs/installation.md
docs/overview.md
docs/quickstart_guide.md
docs/simple_notebook.ipynb
docs/threading_notebook.ipynb
docs/assets/images/astar-v2.gif
docs/assets/images/astar.gif
docs/assets/images/benchmark-astar.png
docs/assets/images/nbastar-v2.gif
docs/assets/images/nbastar.gif
docs/assets/images/tracing-plugin.png
sandbox/timing.py
sandbox/old/pythran_test.ipynb
sandbox/old/sandbox.py
sandbox/old/sandbox2.py
sandbox/old/sandbox_3d.py
brightest_path_lib-1.0.57.dist-info/METADATA
brightest_path_lib-1.0.57.dist-info/WHEEL
brightest_path_lib-1.0.57.dist-info/top_level.txt
brightest_path_lib-1.0.57.dist-info/RECORD
