Metadata-Version: 2.4
Name: brightest-path-lib
Version: 1.0.57
Summary: A library of path-finding algorithms to find the brightest path between points in an image.
Author: Vasudha Jha
License: GNU General Public License, Version 3
Project-URL: Homepage, https://github.com/mapmanager/brightest-path-lib
Project-URL: Issues, https://github.com/mapmanager/brightest-path-lib/issues
Project-URL: CI, https://github.com/mapmanager/brightest-path-lib/actions
Project-URL: Changelog, https://github.com/mapmanager/brightest-path-lib/releases
Requires-Python: >=3.9
License-File: LICENSE
Requires-Dist: numpy
Provides-Extra: dev
Requires-Dist: mkdocs; extra == "dev"
Requires-Dist: mkdocs-material; extra == "dev"
Requires-Dist: mkdocs-jupyter; extra == "dev"
Requires-Dist: mkdocstrings; extra == "dev"
Requires-Dist: mkdocs-material-extensions; extra == "dev"
Provides-Extra: numba
Requires-Dist: numba; extra == "numba"
Provides-Extra: test
Requires-Dist: pytest; extra == "test"
Requires-Dist: pytest-cov; extra == "test"
Requires-Dist: scikit-image; extra == "test"
Requires-Dist: pooch; extra == "test"
Dynamic: license-file
